pyimportcheck/__init__.py
pyimportcheck/__main__.py
pyimportcheck/_cli.py
pyimportcheck/core/__init__.py
pyimportcheck/core/_logger.py
pyimportcheck/core/_utils.py
pyimportcheck/core/detect/__init__.py
pyimportcheck/core/detect/_circular.py
pyimportcheck/core/detect/_exports.py
pyimportcheck/core/detect/_module.py
pyimportcheck/core/detect/types.py
pyimportcheck/core/exception.py
pyimportcheck/core/output/__init__.py
pyimportcheck/core/output/json.py
pyimportcheck/core/output/stdout.py
pyimportcheck/core/scan/__init__.py
pyimportcheck/core/scan/_exports.py
pyimportcheck/core/scan/_imports.py
pyimportcheck/core/scan/_symbols.py
pyimportcheck/core/scan/types.py
pyimportcheck/py.typed
pyimportcheck-0.1.6.dist-info/METADATA
pyimportcheck-0.1.6.dist-info/WHEEL
pyimportcheck-0.1.6.dist-info/entry_points.txt
pyimportcheck-0.1.6.dist-info/RECORD
