Metadata-Version: 2.1
Name: pyimportcheck
Version: 0.1.6
Summary: Python import checker
Author: Yann MAGNIN
Author-email: yann.magnin@protonmail.com
Requires-Python: >=3.9
Classifier: Programming Language :: Python :: 3
Classifier: Programming Language :: Python :: 3.9
Classifier: Programming Language :: Python :: 3.10
Classifier: Programming Language :: Python :: 3.11
Classifier: Programming Language :: Python :: 3.12
Requires-Dist: click (==8.*)
